{
  "button": {
    "small": {
      "icon-size": {
        "value": "{semantic.size.icon.small}",
        "type": "sizing"
      },
      "size": {
        "value": "{semantic.size.component.small}",
        "type": "sizing"
      },
      "padding-left": {
        "value": "{space.150}",
        "type": "spacing"
      },
      "padding-right": {
        "value": "{space.150}",
        "type": "spacing"
      },
      "padding-top": {
        "value": "{space.0}",
        "type": "spacing"
      },
      "padding-bottom": {
        "value": "{space.0}",
        "type": "spacing"
      },
      "space-between": {
        "value": "{space.50}",
        "type": "spacing"
      },
      "border-radius": {
        "value": "{border-radius.4}",
        "type": "borderRadius"
      },
      "border-width": {
        "value": "{border-width.1}",
        "type": "borderWidth"
      }
    },
    "medium": {
      "border-radius": {
        "value": "{border-radius.6}",
        "type": "borderRadius"
      },
      "padding-left": {
        "value": "{space.200}",
        "type": "spacing"
      },
      "padding-right": {
        "value": "{space.200}",
        "type": "spacing"
      },
      "padding-top": {
        "value": "{space.0}",
        "type": "spacing"
      },
      "padding-bottom": {
        "value": "{space.0}",
        "type": "spacing"
      },
      "space-between": {
        "value": "{space.75}",
        "type": "spacing"
      },
      "icon-size": {
        "value": "{semantic.size.icon.medium}",
        "type": "sizing"
      },
      "size": {
        "value": "{semantic.size.component.medium}",
        "type": "sizing"
      },
      "border-width": {
        "value": "{border-width.1}",
        "type": "borderWidth"
      }
    },
    "large": {
      "border-radius": {
        "value": "{border-radius.6}",
        "type": "borderRadius"
      },
      "padding-left": {
        "value": "{space.250}",
        "type": "spacing"
      },
      "padding-right": {
        "value": "{space.250}",
        "type": "spacing"
      },
      "padding-top": {
        "value": "{space.0}",
        "type": "spacing"
      },
      "padding-bottom": {
        "value": "{space.0}",
        "type": "spacing"
      },
      "space-between": {
        "value": "{space.100}",
        "type": "spacing"
      },
      "icon-size": {
        "value": "{semantic.size.icon.medium}",
        "type": "sizing"
      },
      "size": {
        "value": "{semantic.size.component.large}",
        "type": "sizing"
      },
      "border-width": {
        "value": "{border-width.1}",
        "type": "borderWidth"
      },
      "label": {
        "value": "{Base.Label.Large.Default.Semi-bold}",
        "type": "typography"
      }
    },
    "x-large": {
      "border-radius": {
        "value": "{border-radius.8}",
        "type": "borderRadius"
      },
      "icon-size": {
        "value": "{semantic.size.icon.large}",
        "type": "sizing"
      },
      "size": {
        "value": "{semantic.size.component.x-large}",
        "type": "sizing"
      },
      "padding-left": {
        "value": "{space.300}",
        "type": "spacing"
      },
      "padding-right": {
        "value": "{space.300}",
        "type": "spacing"
      },
      "padding-top": {
        "value": "{space.0}",
        "type": "spacing"
      },
      "padding-bottom": {
        "value": "{space.0}",
        "type": "spacing"
      },
      "space-between": {
        "value": "{semantic.spacing.small}",
        "type": "spacing"
      },
      "border-width": {
        "value": "{border-width.1}",
        "type": "borderWidth"
      }
    },
    "focus": {
      "border-width": {
        "value": "{border-width.3}",
        "type": "borderWidth"
      }
    },
    "primary": {
      "default": {
        "bg-color": {
          "value": "{theme.primary.default}",
          "type": "color"
        },
        "border-color": {
          "value": "rgba({button.primary.default.bg-color}, {semantic.opacity.transparent})",
          "type": "color"
        },
        "text-color": {
          "value": "{theme.content.strong-inverse}",
          "type": "color"
        }
      },
      "hover": {
        "bg-color": {
          "value": "{theme.primary.tone}",
          "type": "color"
        },
        "border-color": {
          "value": "rgba({button.primary.hover.bg-color}, {semantic.opacity.transparent})",
          "type": "color"
        },
        "text-color": {
          "value": "{button.primary.default.text-color}",
          "type": "color"
        }
      },
      "active": {
        "bg-color": {
          "value": "{theme.primary.tint}",
          "type": "color"
        },
        "border-color": {
          "value": "rgba({button.primary.active.bg-color}, {semantic.opacity.transparent})",
          "type": "color"
        },
        "text-color": {
          "value": "{button.primary.default.text-color}",
          "type": "color"
        }
      },
      "loading": {
        "bg-color": {
          "value": "{button.primary.default.bg-color}",
          "type": "color"
        },
        "border-color": {
          "value": "rgba({button.primary.loading.bg-color}, {semantic.opacity.transparent})",
          "type": "color"
        },
        "text-color": {
          "value": "{button.primary.default.text-color}",
          "type": "color"
        }
      },
      "disabled": {
        "bg-color": {
          "value": "{theme.background.disabled}",
          "type": "color"
        },
        "border-color": {
          "value": "{colors.transparent}",
          "type": "color"
        },
        "text-color": {
          "value": "{theme.content.disabled}",
          "type": "color"
        }
      }
    },
    "outlined": {
      "default": {
        "bg-color": {
          "value": "{colors.transparent}",
          "type": "color"
        },
        "border-color": {
          "value": "{theme.primary.default}",
          "type": "color"
        },
        "text-color": {
          "value": "{theme.primary.default}",
          "type": "color"
        }
      },
      "hover": {
        "bg-color": {
          "value": "{theme.primary.tone}",
          "type": "color"
        },
        "border-color": {
          "value": "rgba({button.outlined.hover.bg-color}, {semantic.opacity.transparent})",
          "type": "color"
        },
        "text-color": {
          "value": "{theme.content.strong-inverse}",
          "type": "color"
        }
      },
      "active": {
        "bg-color": {
          "value": "{theme.primary.tint}",
          "type": "color"
        },
        "border-color": {
          "value": "rgba({button.outlined.active.bg-color}, {semantic.opacity.transparent})",
          "type": "color"
        },
        "text-color": {
          "value": "{theme.content.strong-inverse}",
          "type": "color"
        }
      },
      "loading": {
        "bg-color": {
          "value": "{theme.primary.default}",
          "type": "color"
        },
        "border-color": {
          "value": "rgba({button.outlined.loading.bg-color}, {semantic.opacity.transparent})",
          "type": "color"
        },
        "text-color": {
          "value": "{theme.content.strong-inverse}",
          "type": "color"
        }
      },
      "disabled": {
        "bg-color": {
          "value": "{theme.background.disabled}",
          "type": "color"
        },
        "border-color": {
          "value": "{colors.transparent}",
          "type": "color"
        },
        "text-color": {
          "value": "{theme.content.disabled}",
          "type": "color"
        }
      }
    },
    "success": {
      "default": {
        "bg-color": {
          "value": "{theme.success.default}",
          "type": "color"
        },
        "border-color": {
          "value": "rgba({button.success.default.bg-color}, {semantic.opacity.transparent})",
          "type": "color"
        },
        "text-color": {
          "value": "{theme.content.strong-inverse}",
          "type": "color"
        }
      },
      "hover": {
        "bg-color": {
          "value": "{theme.success.tone}",
          "type": "color"
        },
        "border-color": {
          "value": "rgba({button.success.hover.bg-color}, {semantic.opacity.transparent})",
          "type": "color"
        },
        "text-color": {
          "value": "{theme.content.strong-inverse}",
          "type": "color"
        }
      },
      "active": {
        "bg-color": {
          "value": "{theme.success.tint}",
          "type": "color"
        },
        "border-color": {
          "value": "rgba({button.success.active.bg-color}, {semantic.opacity.transparent})",
          "type": "color"
        },
        "text-color": {
          "value": "{theme.content.strong-inverse}",
          "type": "color"
        }
      },
      "loading": {
        "bg-color": {
          "value": "{button.success.default.bg-color}",
          "type": "color"
        },
        "border-color": {
          "value": "rgba({button.success.loading.bg-color}, {semantic.opacity.transparent})",
          "type": "color"
        },
        "text-color": {
          "value": "{theme.content.strong-inverse}",
          "type": "color"
        }
      },
      "disabled": {
        "bg-color": {
          "value": "{theme.background.disabled}",
          "type": "color"
        },
        "border-color": {
          "value": "{colors.transparent}",
          "type": "color"
        },
        "text-color": {
          "value": "{theme.content.disabled}",
          "type": "color"
        }
      }
    },
    "secondary": {
      "default": {
        "bg-color": {
          "value": "{theme.special-colors.neutral}",
          "type": "color"
        },
        "border-color": {
          "value": "{colors.transparent}",
          "type": "color"
        },
        "text-color": {
          "value": "{theme.content.strong}",
          "type": "color"
        }
      },
      "hover": {
        "bg-color": {
          "value": "rgba({base.neutral.light.800}, {semantic.opacity.soft})",
          "type": "color"
        },
        "border-color": {
          "value": "{button.secondary.default.border-color}",
          "type": "color"
        },
        "text-color": {
          "value": "{theme.content.strong}",
          "type": "color"
        }
      },
      "active": {
        "bg-color": {
          "value": "rgba({base.neutral.light.800}, {semantic.opacity.medium})",
          "type": "color"
        },
        "border-color": {
          "value": "{button.secondary.default.border-color}",
          "type": "color"
        },
        "text-color": {
          "value": "{theme.content.strong}",
          "type": "color"
        }
      },
      "loading": {
        "bg-color": {
          "value": "{theme.special-colors.neutral}",
          "type": "color"
        },
        "border-color": {
          "value": "{button.secondary.default.border-color}",
          "type": "color"
        },
        "text-color": {
          "value": "{theme.content.strong}",
          "type": "color"
        }
      },
      "disabled": {
        "bg-color": {
          "value": "{theme.background.disabled}",
          "type": "color"
        },
        "border-color": {
          "value": "{button.secondary.default.border-color}",
          "type": "color"
        },
        "text-color": {
          "value": "{theme.content.disabled}",
          "type": "color"
        }
      }
    },
    "clear": {
      "default": {
        "bg-color": {
          "value": "{colors.transparent}",
          "type": "color"
        },
        "border-color": {
          "value": "{colors.transparent}",
          "type": "color"
        },
        "text-color": {
          "value": "{theme.content.default}",
          "type": "color"
        }
      },
      "hover": {
        "bg-color": {
          "value": "{button.secondary.hover.bg-color}",
          "type": "color"
        },
        "border-color": {
          "value": "{colors.transparent}",
          "type": "color"
        },
        "text-color": {
          "value": "{theme.content.strong}",
          "type": "color"
        }
      },
      "active": {
        "bg-color": {
          "value": "{button.secondary.active.bg-color}",
          "type": "color"
        },
        "border-color": {
          "value": "{colors.transparent}",
          "type": "color"
        },
        "text-color": {
          "value": "{theme.content.strong}",
          "type": "color"
        }
      },
      "loading": {
        "bg-color": {
          "value": "{button.secondary.default.bg-color}",
          "type": "color"
        },
        "border-color": {
          "value": "{colors.transparent}",
          "type": "color"
        },
        "text-color": {
          "value": "{theme.content.default}",
          "type": "color"
        }
      },
      "disabled": {
        "bg-color": {
          "value": "{theme.background.disabled}",
          "type": "color"
        },
        "border-color": {
          "value": "{colors.transparent}",
          "type": "color"
        },
        "text-color": {
          "value": "{theme.content.disabled}",
          "type": "color"
        }
      }
    },
    "ghost": {
      "default": {
        "bg-color": {
          "value": "{colors.transparent}",
          "type": "color"
        },
        "border-color": {
          "value": "{theme.border.light}",
          "type": "color"
        },
        "text-color": {
          "value": "{theme.content.default}",
          "type": "color"
        }
      },
      "hover": {
        "bg-color": {
          "value": "{button.secondary.default.bg-color}",
          "type": "color"
        },
        "border-color": {
          "value": "{button.secondary.hover.border-color}",
          "type": "color"
        },
        "text-color": {
          "value": "{theme.content.strong}",
          "type": "color"
        }
      },
      "active": {
        "bg-color": {
          "value": "{button.secondary.active.bg-color}",
          "type": "color"
        },
        "border-color": {
          "value": "{button.secondary.active.border-color}",
          "type": "color"
        },
        "text-color": {
          "value": "{theme.content.strong}",
          "type": "color"
        }
      },
      "loading": {
        "bg-color": {
          "value": "{theme.special-colors.neutral}",
          "type": "color"
        },
        "border-color": {
          "value": "{button.secondary.loading.border-color}",
          "type": "color"
        },
        "text-color": {
          "value": "{theme.content.default}",
          "type": "color"
        }
      },
      "disabled": {
        "bg-color": {
          "value": "{theme.background.disabled}",
          "type": "color"
        },
        "border-color": {
          "value": "{button.secondary.disabled.border-color}",
          "type": "color"
        },
        "text-color": {
          "value": "{theme.content.disabled}",
          "type": "color"
        }
      }
    }
  },
  "icon-button": {
    "x-small": {
      "icon-size": {
        "value": "{semantic.size.icon.small}",
        "type": "sizing"
      },
      "size": {
        "value": "{semantic.size.component.x-small}",
        "type": "sizing"
      }
    },
    "small": {
      "icon-size": {
        "value": "{semantic.size.icon.medium}",
        "type": "sizing"
      },
      "size": {
        "value": "{semantic.size.component.small}",
        "type": "sizing"
      }
    },
    "medium": {
      "icon-size": {
        "value": "{semantic.size.icon.large}",
        "type": "sizing"
      },
      "size": {
        "value": "{semantic.size.component.medium}",
        "type": "sizing"
      }
    },
    "large": {
      "icon-size": {
        "value": "{semantic.size.icon.large}",
        "type": "sizing"
      },
      "size": {
        "value": "{semantic.size.component.large}",
        "type": "sizing"
      }
    },
    "x-large": {
      "icon-size": {
        "value": "{semantic.size.icon.large}",
        "type": "sizing"
      },
      "size": {
        "value": "{semantic.size.component.x-large}",
        "type": "sizing"
      }
    }
  },
  "input": {
    "label-spacing": {
      "value": "{semantic.spacing.small}",
      "type": "spacing"
    },
    "helper-spacing": {
      "value": "{semantic.spacing.none}",
      "type": "spacing"
    },
    "background-color": {
      "value": "{theme.background.surface}",
      "type": "color"
    },
    "background-color-alt": {
      "value": "{theme.background.muted}",
      "type": "color"
    },
    "border-color": {
      "value": "{theme.border.medium}",
      "type": "color"
    },
    "label-text-color": {
      "value": "{theme.content.strong}",
      "type": "color"
    },
    "entry-text-color": {
      "value": "{theme.content.strong}",
      "type": "color"
    },
    "helper-text-color": {
      "value": "{theme.content.default}",
      "type": "color"
    },
    "error-text-color": {
      "value": "{theme.danger.default}",
      "type": "color"
    },
    "placeholder-text-color": {
      "value": "{theme.content.disabled}",
      "type": "color"
    },
    "icon-color": {
      "value": "{theme.content.default}",
      "type": "color"
    },
    "border-focus": {
      "value": "{theme.primary.default}",
      "type": "color"
    },
    "border-error": {
      "value": "{theme.danger.default}",
      "type": "color"
    }
  }
}