{
  "opacity": {
    "0": {
      "value": "0",
      "type": "opacity"
    },
    "8": {
      "value": ".08",
      "type": "opacity"
    },
    "16": {
      "value": ".16",
      "type": "opacity"
    },
    "24": {
      "value": ".24",
      "type": "opacity"
    },
    "32": {
      "value": ".32",
      "type": "opacity"
    },
    "40": {
      "value": ".4",
      "type": "opacity"
    },
    "48": {
      "value": ".48",
      "type": "opacity"
    },
    "56": {
      "value": ".56",
      "type": "opacity"
    },
    "64": {
      "value": ".64",
      "type": "opacity"
    },
    "72": {
      "value": ".72",
      "type": "opacity"
    },
    "80": {
      "value": ".8",
      "type": "opacity"
    },
    "88": {
      "value": ".88",
      "type": "opacity"
    },
    "96": {
      "value": "0.96",
      "type": "opacity"
    }
  },
  "space": {
    "0": {
      "value": "0px",
      "type": "spacing"
    },
    "25": {
      "value": "2",
      "type": "spacing"
    },
    "50": {
      "value": "4",
      "type": "spacing"
    },
    "75": {
      "value": "6",
      "type": "spacing"
    },
    "100": {
      "value": "8",
      "type": "spacing"
    },
    "125": {
      "value": "10",
      "type": "spacing"
    },
    "150": {
      "value": "12",
      "type": "spacing"
    },
    "175": {
      "value": "14",
      "type": "spacing"
    },
    "200": {
      "value": "16",
      "type": "spacing"
    },
    "250": {
      "value": "20",
      "type": "spacing"
    },
    "300": {
      "value": "24",
      "type": "spacing"
    },
    "400": {
      "value": "32",
      "type": "spacing"
    },
    "500": {
      "value": "40",
      "type": "spacing"
    },
    "600": {
      "value": "48",
      "type": "spacing"
    },
    "700": {
      "value": "56",
      "type": "spacing"
    },
    "800": {
      "value": "64",
      "type": "spacing"
    }
  },
  "size": {
    "0": {
      "value": "0",
      "type": "sizing"
    },
    "1": {
      "value": "1",
      "type": "sizing"
    },
    "25": {
      "value": "2",
      "type": "sizing"
    },
    "50": {
      "value": "4",
      "type": "sizing"
    },
    "75": {
      "value": "6",
      "type": "sizing"
    },
    "100": {
      "value": "8",
      "type": "sizing"
    },
    "125": {
      "value": "10",
      "type": "sizing"
    },
    "150": {
      "value": "12",
      "type": "sizing"
    },
    "175": {
      "value": "14",
      "type": "sizing"
    },
    "200": {
      "value": "16",
      "type": "sizing"
    },
    "225": {
      "value": "18",
      "type": "sizing"
    },
    "250": {
      "value": "20",
      "type": "sizing"
    },
    "275": {
      "value": "22",
      "type": "sizing"
    },
    "300": {
      "value": "24",
      "type": "sizing"
    },
    "350": {
      "value": "28px",
      "type": "sizing"
    },
    "400": {
      "value": "32",
      "type": "sizing"
    },
    "450": {
      "value": "36",
      "type": "sizing"
    },
    "500": {
      "value": "40",
      "type": "sizing"
    },
    "600": {
      "value": "48",
      "type": "sizing"
    },
    "700": {
      "value": "56",
      "type": "sizing"
    },
    "750": {
      "value": "60",
      "type": "sizing"
    },
    "800": {
      "value": "64",
      "type": "sizing"
    },
    "1000": {
      "value": "80",
      "type": "sizing"
    },
    "1200": {
      "value": "96",
      "type": "sizing"
    },
    "1500": {
      "value": "120",
      "type": "sizing"
    },
    "2000": {
      "value": "160",
      "type": "sizing"
    },
    "2500": {
      "value": "200",
      "type": "sizing"
    }
  },
  "border-radius": {
    "0": {
      "value": "0",
      "type": "borderRadius"
    },
    "2": {
      "value": "2",
      "type": "borderRadius"
    },
    "4": {
      "value": "4",
      "type": "borderRadius"
    },
    "6": {
      "value": "6",
      "type": "borderRadius"
    },
    "8": {
      "value": "8",
      "type": "borderRadius"
    },
    "12": {
      "value": "12",
      "type": "borderRadius"
    },
    "16": {
      "value": "16",
      "type": "borderRadius"
    },
    "999": {
      "value": "999",
      "type": "borderRadius"
    }
  },
  "border-width": {
    "0": {
      "value": "0",
      "type": "borderWidth"
    },
    "1": {
      "value": "1",
      "type": "borderWidth"
    },
    "2": {
      "value": "2",
      "type": "borderWidth"
    },
    "3": {
      "value": "3",
      "type": "borderWidth"
    }
  },
  "font-size": {
    "9": {
      "value": "9",
      "type": "fontSizes"
    },
    "10": {
      "value": "10",
      "type": "fontSizes"
    },
    "11": {
      "value": "11",
      "type": "fontSizes"
    },
    "12": {
      "value": "12",
      "type": "fontSizes"
    },
    "13": {
      "value": "13",
      "type": "fontSizes"
    },
    "14": {
      "value": "14",
      "type": "fontSizes"
    },
    "15": {
      "value": "15",
      "type": "fontSizes"
    },
    "16": {
      "value": "16",
      "type": "fontSizes"
    },
    "18": {
      "value": "18",
      "type": "fontSizes"
    },
    "20": {
      "value": "20",
      "type": "fontSizes"
    },
    "24": {
      "value": "24",
      "type": "fontSizes"
    },
    "28": {
      "value": "28",
      "type": "fontSizes"
    },
    "32": {
      "value": "32",
      "type": "fontSizes"
    },
    "40": {
      "value": "40",
      "type": "fontSizes"
    },
    "48": {
      "value": "48",
      "type": "fontSizes"
    },
    "56": {
      "value": "56",
      "type": "fontSizes"
    },
    "64": {
      "value": "64",
      "type": "fontSizes"
    },
    "72": {
      "value": "72",
      "type": "fontSizes"
    },
    "80": {
      "value": "80",
      "type": "fontSizes"
    }
  },
  "font-weight": {
    "regular": {
      "value": "Regular",
      "type": "fontWeights"
    },
    "medium": {
      "value": "Medium",
      "type": "fontWeights"
    },
    "semi-bold": {
      "value": "Semi Bold",
      "type": "fontWeights"
    },
    "bold": {
      "value": "Bold",
      "type": "fontWeights"
    }
  },
  "font-family": {
    "inter": {
      "value": "Inter",
      "type": "fontFamilies"
    },
    "primary": {
      "value": "Inter",
      "type": "fontFamilies"
    }
  },
  "base": {
    "white": {
      "value": "{colors.white}",
      "type": "color"
    },
    "black": {
      "value": "{colors.black}",
      "type": "color"
    },
    "transparent": {
      "value": "{colors.transparent}",
      "type": "color"
    },
    "primary": {
      "100": {
        "value": "{colors.indigo.100}",
        "type": "color"
      },
      "200": {
        "value": "{colors.indigo.200}",
        "type": "color"
      },
      "300": {
        "value": "{colors.indigo.300}",
        "type": "color"
      },
      "400": {
        "value": "{colors.indigo.400}",
        "type": "color"
      },
      "500": {
        "value": "{colors.indigo.500}",
        "type": "color"
      },
      "600": {
        "value": "{colors.indigo.600}",
        "type": "color"
      },
      "700": {
        "value": "{colors.indigo.700}",
        "type": "color"
      },
      "800": {
        "value": "{colors.indigo.800}",
        "type": "color"
      },
      "900": {
        "value": "{colors.indigo.900}",
        "type": "color"
      }
    },
    "help": {
      "100": {
        "value": "{colors.blue.100}",
        "type": "color"
      },
      "200": {
        "value": "{colors.blue.200}",
        "type": "color"
      },
      "300": {
        "value": "{colors.blue.300}",
        "type": "color"
      },
      "400": {
        "value": "{colors.blue.400}",
        "type": "color"
      },
      "500": {
        "value": "{colors.blue.500}",
        "type": "color"
      },
      "600": {
        "value": "{colors.blue.600}",
        "type": "color"
      },
      "700": {
        "value": "{colors.blue.700}",
        "type": "color"
      },
      "800": {
        "value": "{colors.blue.800}",
        "type": "color"
      },
      "900": {
        "value": "{colors.blue.900}",
        "type": "color"
      }
    },
    "success": {
      "100": {
        "value": "{colors.green.100}",
        "type": "color"
      },
      "200": {
        "value": "{colors.green.200}",
        "type": "color"
      },
      "300": {
        "value": "{colors.green.300}",
        "type": "color"
      },
      "400": {
        "value": "{colors.green.400}",
        "type": "color"
      },
      "500": {
        "value": "{colors.green.500}",
        "type": "color"
      },
      "600": {
        "value": "{colors.green.600}",
        "type": "color"
      },
      "700": {
        "value": "{colors.green.700}",
        "type": "color"
      },
      "800": {
        "value": "{colors.green.800}",
        "type": "color"
      },
      "900": {
        "value": "{colors.green.900}",
        "type": "color"
      }
    },
    "warning": {
      "100": {
        "value": "{colors.orange.100}",
        "type": "color"
      },
      "200": {
        "value": "{colors.orange.200}",
        "type": "color"
      },
      "300": {
        "value": "{colors.orange.300}",
        "type": "color"
      },
      "400": {
        "value": "{colors.orange.400}",
        "type": "color"
      },
      "500": {
        "value": "{colors.orange.500}",
        "type": "color"
      },
      "600": {
        "value": "{colors.orange.600}",
        "type": "color"
      },
      "700": {
        "value": "{colors.orange.700}",
        "type": "color"
      },
      "800": {
        "value": "{colors.orange.800}",
        "type": "color"
      },
      "900": {
        "value": "{colors.orange.900}",
        "type": "color"
      }
    },
    "danger": {
      "100": {
        "value": "{colors.red.100}",
        "type": "color"
      },
      "200": {
        "value": "{colors.red.200}",
        "type": "color"
      },
      "300": {
        "value": "{colors.red.300}",
        "type": "color"
      },
      "400": {
        "value": "{colors.red.400}",
        "type": "color"
      },
      "500": {
        "value": "{colors.red.500}",
        "type": "color"
      },
      "600": {
        "value": "{colors.red.600}",
        "type": "color"
      },
      "700": {
        "value": "{colors.red.700}",
        "type": "color"
      },
      "800": {
        "value": "{colors.red.800}",
        "type": "color"
      },
      "900": {
        "value": "{colors.red.900}",
        "type": "color"
      }
    },
    "neutral": {
      "light": {
        "100": {
          "value": "{colors.slate.light.100}",
          "type": "color"
        },
        "200": {
          "value": "{colors.slate.light.200}",
          "type": "color"
        },
        "300": {
          "value": "{colors.slate.light.300}",
          "type": "color"
        },
        "400": {
          "value": "{colors.slate.light.400}",
          "type": "color"
        },
        "500": {
          "value": "{colors.slate.light.500}",
          "type": "color"
        },
        "600": {
          "value": "{colors.slate.light.600}",
          "type": "color"
        },
        "700": {
          "value": "{colors.slate.light.700}",
          "type": "color"
        },
        "800": {
          "value": "{colors.slate.light.800}",
          "type": "color"
        },
        "900": {
          "value": "{colors.slate.light.900}",
          "type": "color"
        }
      },
      "dark": {
        "100": {
          "value": "{colors.slate.dark.100}",
          "type": "color"
        },
        "200": {
          "value": "{colors.slate.dark.200}",
          "type": "color"
        },
        "300": {
          "value": "{colors.slate.dark.300}",
          "type": "color"
        },
        "400": {
          "value": "{colors.slate.dark.400}",
          "type": "color"
        },
        "500": {
          "value": "{colors.slate.dark.500}",
          "type": "color"
        },
        "600": {
          "value": "{colors.slate.dark.600}",
          "type": "color"
        },
        "700": {
          "value": "{colors.slate.dark.700}",
          "type": "color"
        },
        "800": {
          "value": "{colors.slate.dark.800}",
          "type": "color"
        },
        "900": {
          "value": "{colors.slate.dark.900}",
          "type": "color"
        }
      }
    },
    "black-alpha": {
      "100": {
        "value": "rgba({colors.black}, {opacity.8})",
        "type": "color"
      },
      "200": {
        "value": "rgba({colors.black}, {opacity.16})",
        "type": "color"
      },
      "300": {
        "value": "rgba({colors.black}, {opacity.24})",
        "type": "color"
      },
      "400": {
        "value": "rgba({colors.black}, {opacity.32})",
        "type": "color"
      },
      "500": {
        "value": "rgba({colors.black}, {opacity.40})",
        "type": "color"
      },
      "600": {
        "value": "rgba({colors.black}, {opacity.48})",
        "type": "color"
      },
      "700": {
        "value": "rgba({colors.black}, {opacity.56})",
        "type": "color"
      },
      "800": {
        "value": "rgba({colors.black}, {opacity.64})",
        "type": "color"
      },
      "900": {
        "value": "rgba({colors.black}, {opacity.72})",
        "type": "color"
      },
      "1000": {
        "value": "rgba({colors.black}, {opacity.80})",
        "type": "color"
      }
    },
    "white-alpha": {
      "100": {
        "value": "rgba({colors.white}, {opacity.8})",
        "type": "color"
      },
      "200": {
        "value": "rgba({colors.white}, {opacity.16})",
        "type": "color"
      },
      "300": {
        "value": "rgba({colors.white}, {opacity.24})",
        "type": "color"
      },
      "400": {
        "value": "rgba({colors.white}, {opacity.32})",
        "type": "color"
      },
      "500": {
        "value": "rgba({colors.white}, {opacity.40})",
        "type": "color"
      },
      "600": {
        "value": "rgba({colors.white}, {opacity.48})",
        "type": "color"
      },
      "700": {
        "value": "rgba({colors.white}, {opacity.56})",
        "type": "color"
      },
      "800": {
        "value": "rgba({colors.white}, {opacity.64})",
        "type": "color"
      },
      "900": {
        "value": "rgba({colors.white}, {opacity.72})",
        "type": "color"
      },
      "1000": {
        "value": "rgba({colors.white}, {opacity.80})",
        "type": "color"
      }
    }
  },
  "line-height": {
    "100": {
      "value": "100%",
      "type": "lineHeights"
    },
    "120": {
      "value": "120%",
      "type": "lineHeights"
    }
  },
  "text-case": {
    "uppercase": {
      "value": "uppercase",
      "type": "textCase"
    }
  }
}